odoo/addons/vertical_carsharing/__init__.py
odoo/addons/vertical_carsharing/__manifest__.py
odoo/addons/vertical_carsharing/data/sm_account_journal.xml
odoo/addons/vertical_carsharing/email_tmpl/notification_email.xml
odoo/addons/vertical_carsharing/models/__init__.py
odoo/addons/vertical_carsharing/models/models_cs_task.py
odoo/addons/vertical_carsharing/models/models_sm_bank.py
odoo/addons/vertical_carsharing/models/models_sm_member.py
odoo/addons/vertical_carsharing/models/product.py
odoo/addons/vertical_carsharing/static/src/img/carsharing.png
odoo/addons/vertical_carsharing/static/src/scss/primary_variables.scss
odoo/addons/vertical_carsharing/views/account_invoice_view.xml
odoo/addons/vertical_carsharing/views/product_view.xml
odoo/addons/vertical_carsharing/views/views.xml
odoo/addons/vertical_carsharing/views/views_cs_task.xml
odoo/addons/vertical_carsharing/views/views_members.xml
odoo12_addon_vertical_carsharing-12.0.0.1.7.dist-info/METADATA
odoo12_addon_vertical_carsharing-12.0.0.1.7.dist-info/WHEEL
odoo12_addon_vertical_carsharing-12.0.0.1.7.dist-info/top_level.txt
odoo12_addon_vertical_carsharing-12.0.0.1.7.dist-info/RECORD
