Metadata-Version: 2.1
Name: odoo12-addon-vertical-carsharing
Version: 12.0.0.1.7
Summary: Modules to masnage your carsharing enerprise using TMF reservation app
Home-page: https://www.sommobilitat.coop
Author: Som Mobilitat
License: UNKNOWN
Platform: UNKNOWN
Classifier: Programming Language :: Python
Classifier: Framework :: Odoo
Classifier: Framework :: Odoo :: 12.0
Requires-Python: >=3.5
Requires-Dist: odoo12-addon-product-analytic
Requires-Dist: odoo <12.1dev,>=12.0a
